promptshield_ptit/__init__.py
promptshield_ptit/input_processor.py
promptshield_ptit/promptshield_ptit.py
promptshield_ptit/split_chunks.py
promptshield_ptit-0.1.4.dist-info/METADATA
promptshield_ptit-0.1.4.dist-info/WHEEL
promptshield_ptit-0.1.4.dist-info/top_level.txt
promptshield_ptit-0.1.4.dist-info/RECORD
